<?xml version="1.0" encoding="UTF-8"?>
<vivadoHLSLog:LogRoot xmlns:vivadoHLSLog="www.xilinx.com/vivadoHLSLog">
  <errorLogs>
    <logs>
      <synLog/>
      <simLog/>
      <mgLog/>
      <packageLog/>
      <csimLog/>
    </logs>
  </errorLogs>
  <warningLogs>
    <logs>
      <synLog>
        <logs message="WARNING: [RTMG 210-274] Memory 'calcLayerDetAndTribs' is read-only, switch it to a ROM." projectName="HLS_SURF_Simplified" solutionName="solution1" date="2020-08-27T17:06:14.325+0800" type="Warning"/>
        <logs message="WARNING: [RTMG 210-274] Memory 'calcLayerDetAndTrhbi' is read-only, switch it to a ROM." projectName="HLS_SURF_Simplified" solutionName="solution1" date="2020-08-27T17:06:14.221+0800" type="Warning"/>
        <logs message="WARNING: [RTMG 210-274] Memory 'calcLayerDetAndTrg8j' is read-only, switch it to a ROM." projectName="HLS_SURF_Simplified" solutionName="solution1" date="2020-08-27T17:06:14.094+0800" type="Warning"/>
        <logs message="WARNING: [RTMG 210-274] Memory 'calcLayerDetAndTrfYi' is read-only, switch it to a ROM." projectName="HLS_SURF_Simplified" solutionName="solution1" date="2020-08-27T17:06:13.997+0800" type="Warning"/>
        <logs message="WARNING: [RTMG 210-274] Memory 'calcLayerDetAndTreOg' is read-only, switch it to a ROM." projectName="HLS_SURF_Simplified" solutionName="solution1" date="2020-08-27T17:06:13.897+0800" type="Warning"/>
        <logs message="WARNING: [RTGEN 206-101] RTL name 'fifo_w32_d2_A' is changed to 'fifo_w32_d2_A_x' due to conflict." projectName="HLS_SURF_Simplified" solutionName="solution1" date="2020-08-27T17:06:11.798+0800" type="Warning"/>
        <logs message="WARNING: [RTGEN 206-101] Setting dangling out port 'HessianDetector/m_axi_pointNumber_RREADY' to 0." projectName="HLS_SURF_Simplified" solutionName="solution1" date="2020-08-27T17:06:10.840+0800" type="Warning"/>
        <logs message="WARNING: [RTGEN 206-101] Setting dangling out port 'HessianDetector/m_axi_pointNumber_ARUSER' to 0." projectName="HLS_SURF_Simplified" solutionName="solution1" date="2020-08-27T17:06:10.823+0800" type="Warning"/>
        <logs message="WARNING: [RTGEN 206-101] Setting dangling out port 'HessianDetector/m_axi_pointNumber_ARREGION' to 0." projectName="HLS_SURF_Simplified" solutionName="solution1" date="2020-08-27T17:06:10.805+0800" type="Warning"/>
        <logs message="WARNING: [RTGEN 206-101] Setting dangling out port 'HessianDetector/m_axi_pointNumber_ARQOS' to 0." projectName="HLS_SURF_Simplified" solutionName="solution1" date="2020-08-27T17:06:10.783+0800" type="Warning"/>
        <logs message="WARNING: [RTGEN 206-101] Setting dangling out port 'HessianDetector/m_axi_pointNumber_ARPROT' to 0." projectName="HLS_SURF_Simplified" solutionName="solution1" date="2020-08-27T17:06:10.765+0800" type="Warning"/>
        <logs message="WARNING: [RTGEN 206-101] Setting dangling out port 'HessianDetector/m_axi_pointNumber_ARCACHE' to 0." projectName="HLS_SURF_Simplified" solutionName="solution1" date="2020-08-27T17:06:10.746+0800" type="Warning"/>
        <logs message="WARNING: [RTGEN 206-101] Setting dangling out port 'HessianDetector/m_axi_pointNumber_ARLOCK' to 0." projectName="HLS_SURF_Simplified" solutionName="solution1" date="2020-08-27T17:06:10.729+0800" type="Warning"/>
        <logs message="WARNING: [RTGEN 206-101] Setting dangling out port 'HessianDetector/m_axi_pointNumber_ARBURST' to 0." projectName="HLS_SURF_Simplified" solutionName="solution1" date="2020-08-27T17:06:10.709+0800" type="Warning"/>
        <logs message="WARNING: [RTGEN 206-101] Setting dangling out port 'HessianDetector/m_axi_pointNumber_ARSIZE' to 0." projectName="HLS_SURF_Simplified" solutionName="solution1" date="2020-08-27T17:06:10.685+0800" type="Warning"/>
        <logs message="WARNING: [RTGEN 206-101] Setting dangling out port 'HessianDetector/m_axi_pointNumber_ARLEN' to 0." projectName="HLS_SURF_Simplified" solutionName="solution1" date="2020-08-27T17:06:10.661+0800" type="Warning"/>
        <logs message="WARNING: [RTGEN 206-101] Setting dangling out port 'HessianDetector/m_axi_pointNumber_ARID' to 0." projectName="HLS_SURF_Simplified" solutionName="solution1" date="2020-08-27T17:06:10.625+0800" type="Warning"/>
        <logs message="WARNING: [RTGEN 206-101] Setting dangling out port 'HessianDetector/m_axi_pointNumber_ARADDR' to 0." projectName="HLS_SURF_Simplified" solutionName="solution1" date="2020-08-27T17:06:10.600+0800" type="Warning"/>
        <logs message="WARNING: [RTGEN 206-101] Setting dangling out port 'HessianDetector/m_axi_pointNumber_ARVALID' to 0." projectName="HLS_SURF_Simplified" solutionName="solution1" date="2020-08-27T17:06:10.579+0800" type="Warning"/>
        <logs message="WARNING: [RTGEN 206-101] Setting dangling out port 'HessianDetector/m_axi_keyPoints_V_RREADY' to 0." projectName="HLS_SURF_Simplified" solutionName="solution1" date="2020-08-27T17:06:10.560+0800" type="Warning"/>
        <logs message="WARNING: [RTGEN 206-101] Setting dangling out port 'HessianDetector/m_axi_keyPoints_V_ARUSER' to 0." projectName="HLS_SURF_Simplified" solutionName="solution1" date="2020-08-27T17:06:10.541+0800" type="Warning"/>
        <logs message="WARNING: [RTGEN 206-101] Setting dangling out port 'HessianDetector/m_axi_keyPoints_V_ARREGION' to 0." projectName="HLS_SURF_Simplified" solutionName="solution1" date="2020-08-27T17:06:10.460+0800" type="Warning"/>
        <logs message="WARNING: [RTGEN 206-101] Setting dangling out port 'HessianDetector/m_axi_keyPoints_V_ARQOS' to 0." projectName="HLS_SURF_Simplified" solutionName="solution1" date="2020-08-27T17:06:10.441+0800" type="Warning"/>
        <logs message="WARNING: [RTGEN 206-101] Setting dangling out port 'HessianDetector/m_axi_keyPoints_V_ARPROT' to 0." projectName="HLS_SURF_Simplified" solutionName="solution1" date="2020-08-27T17:06:10.422+0800" type="Warning"/>
        <logs message="WARNING: [RTGEN 206-101] Setting dangling out port 'HessianDetector/m_axi_keyPoints_V_ARCACHE' to 0." projectName="HLS_SURF_Simplified" solutionName="solution1" date="2020-08-27T17:06:10.402+0800" type="Warning"/>
        <logs message="WARNING: [RTGEN 206-101] Setting dangling out port 'HessianDetector/m_axi_keyPoints_V_ARLOCK' to 0." projectName="HLS_SURF_Simplified" solutionName="solution1" date="2020-08-27T17:06:10.382+0800" type="Warning"/>
        <logs message="WARNING: [RTGEN 206-101] Setting dangling out port 'HessianDetector/m_axi_keyPoints_V_ARBURST' to 0." projectName="HLS_SURF_Simplified" solutionName="solution1" date="2020-08-27T17:06:10.363+0800" type="Warning"/>
        <logs message="WARNING: [RTGEN 206-101] Setting dangling out port 'HessianDetector/m_axi_keyPoints_V_ARSIZE' to 0." projectName="HLS_SURF_Simplified" solutionName="solution1" date="2020-08-27T17:06:10.347+0800" type="Warning"/>
        <logs message="WARNING: [RTGEN 206-101] Setting dangling out port 'HessianDetector/m_axi_keyPoints_V_ARLEN' to 0." projectName="HLS_SURF_Simplified" solutionName="solution1" date="2020-08-27T17:06:10.329+0800" type="Warning"/>
        <logs message="WARNING: [RTGEN 206-101] Setting dangling out port 'HessianDetector/m_axi_keyPoints_V_ARID' to 0." projectName="HLS_SURF_Simplified" solutionName="solution1" date="2020-08-27T17:06:10.313+0800" type="Warning"/>
        <logs message="WARNING: [RTGEN 206-101] Setting dangling out port 'HessianDetector/m_axi_keyPoints_V_ARADDR' to 0." projectName="HLS_SURF_Simplified" solutionName="solution1" date="2020-08-27T17:06:10.298+0800" type="Warning"/>
        <logs message="WARNING: [RTGEN 206-101] Setting dangling out port 'HessianDetector/m_axi_keyPoints_V_ARVALID' to 0." projectName="HLS_SURF_Simplified" solutionName="solution1" date="2020-08-27T17:06:10.283+0800" type="Warning"/>
        <logs message="WARNING: [RTGEN 206-101] Register 'tmpPointNum' is power-on initialization." projectName="HLS_SURF_Simplified" solutionName="solution1" date="2020-08-27T17:06:08.465+0800" type="Warning"/>
        <logs message="WARNING: [RTGEN 206-101] Register 'MSB_V_1' is power-on initialization." projectName="HLS_SURF_Simplified" solutionName="solution1" date="2020-08-27T17:06:08.403+0800" type="Warning"/>
        <logs message="WARNING: [RTGEN 206-101] Register 'bRow_V_2' is power-on initialization." projectName="HLS_SURF_Simplified" solutionName="solution1" date="2020-08-27T17:06:08.389+0800" type="Warning"/>
        <logs message="WARNING: [RTGEN 206-101] Register 'bRow_V_1' is power-on initialization." projectName="HLS_SURF_Simplified" solutionName="solution1" date="2020-08-27T17:06:08.375+0800" type="Warning"/>
        <logs message="WARNING: [RTGEN 206-101] Register 'bRow_V_0' is power-on initialization." projectName="HLS_SURF_Simplified" solutionName="solution1" date="2020-08-27T17:06:08.361+0800" type="Warning"/>
        <logs message="WARNING: [RTGEN 206-101] Register 'MSB_V' is power-on initialization." projectName="HLS_SURF_Simplified" solutionName="solution1" date="2020-08-27T17:06:06.387+0800" type="Warning"/>
        <logs message="WARNING: [SYN 201-103] Legalizing function name 'surf_Simplified.entr' to 'surf_Simplified_entr'." projectName="HLS_SURF_Simplified" solutionName="solution1" date="2020-08-27T17:05:55.856+0800" type="Warning"/>
        <logs message="WARNING: [XFORM 203-631] Renaming function 'calcLayerDetAndTrace8' to 'calcLayerDetAndTrace' (mSURF.cpp:175)" projectName="HLS_SURF_Simplified" solutionName="solution1" date="2020-08-27T17:05:55.794+0800" type="Warning"/>
        <logs message="WARNING: [XFORM 203-631] Renaming function 'surf_Simplified.entry11' to 'surf_Simplified.entr' " projectName="HLS_SURF_Simplified" solutionName="solution1" date="2020-08-27T17:05:55.518+0800" type="Warning"/>
        <logs message="WARNING: [XFORM 203-631] Renaming function 'Block_codeRepl47_proc' to 'Block_codeRepl47_pro' (top.cpp:34:2)" projectName="HLS_SURF_Simplified" solutionName="solution1" date="2020-08-27T17:05:55.503+0800" type="Warning"/>
        <logs message="WARNING: [XFORM 203-631] Renaming function 'hls::AXIvideo2Mat&lt;24, 600, 800, 4096>' to 'AXIvideo2Mat' (C:/Xilinx/Vivado/2018.3/common/technology/autopilot/hls/hls_video_io.h:49:9)" projectName="HLS_SURF_Simplified" solutionName="solution1" date="2020-08-27T17:05:54.449+0800" type="Warning"/>
        <logs message="WARNING: [XFORM 203-631] Renaming function 'my::SURF::HessianDetector' to 'HessianDetector' (mSURF.cpp:529)" projectName="HLS_SURF_Simplified" solutionName="solution1" date="2020-08-27T17:05:54.433+0800" type="Warning"/>
        <logs message="WARNING: [XFORM 203-631] Renaming function 'my::SURF::calcHaarPattern_x_y' to 'calcHaarPattern_x_y' (mSURF.cpp:100)" projectName="HLS_SURF_Simplified" solutionName="solution1" date="2020-08-27T17:05:54.418+0800" type="Warning"/>
        <logs message="WARNING: [XFORM 203-631] Renaming function 'my::SURF::calcLayerDetAndTrace8797' to 'calcLayerDetAndTrace' (mSURF.cpp:175)" projectName="HLS_SURF_Simplified" solutionName="solution1" date="2020-08-27T17:05:54.401+0800" type="Warning"/>
        <logs message="WARNING: [XFORM 203-631] Renaming function 'my::SURF::findCharacteristicPoint88' to 'findCharacteristicPo' (mSURF.cpp:371:10)" projectName="HLS_SURF_Simplified" solutionName="solution1" date="2020-08-27T17:05:54.386+0800" type="Warning"/>
        <logs message="WARNING: [XFORM 203-631] Renaming function 'my::SURF::integralImg' to 'integralImg' (mSURF.cpp:51)" projectName="HLS_SURF_Simplified" solutionName="solution1" date="2020-08-27T17:05:54.373+0800" type="Warning"/>
        <logs message="WARNING: [XFORM 203-561] Updating loop lower bound from 0 to 600 for loop 'loop_height' in function 'hls::AXIvideo2Mat&lt;24, 600, 800, 4096>'." projectName="HLS_SURF_Simplified" solutionName="solution1" date="2020-08-27T17:05:52.438+0800" type="Warning"/>
        <logs message="WARNING: [XFORM 203-561] Updating loop lower bound from 0 to 800 for loop 'loop_width' in function 'hls::AXIvideo2Mat&lt;24, 600, 800, 4096>'." projectName="HLS_SURF_Simplified" solutionName="solution1" date="2020-08-27T17:05:52.262+0800" type="Warning"/>
        <logs message="WARNING: [XFORM 203-561] Updating loop lower bound from 1 to 591 for loop 'findCharacteristicPoint_r0' (mSURF.cpp:414:1) in function 'my::SURF::findCharacteristicPoint88'." projectName="HLS_SURF_Simplified" solutionName="solution1" date="2020-08-27T17:05:52.245+0800" type="Warning"/>
        <logs message="WARNING: [XFORM 203-561] Updating loop upper bound from 559 to 591 for loop 'findCharacteristicPoint_r0' (mSURF.cpp:414:1) in function 'my::SURF::findCharacteristicPoint88'." projectName="HLS_SURF_Simplified" solutionName="solution1" date="2020-08-27T17:05:52.228+0800" type="Warning"/>
        <logs message="WARNING: [XFORM 203-561] Updating loop lower bound from 1 to 791 for loop 'findCharacteristicPoint_c0' (mSURF.cpp:446:1) in function 'my::SURF::findCharacteristicPoint88'." projectName="HLS_SURF_Simplified" solutionName="solution1" date="2020-08-27T17:05:52.214+0800" type="Warning"/>
        <logs message="WARNING: [XFORM 203-561] Updating loop upper bound from 858 to 791 for loop 'findCharacteristicPoint_c0' (mSURF.cpp:446:1) in function 'my::SURF::findCharacteristicPoint88'." projectName="HLS_SURF_Simplified" solutionName="solution1" date="2020-08-27T17:05:52.200+0800" type="Warning"/>
        <logs message="WARNING: [XFORM 203-561] Updating loop lower bound from 1 to 601 for loop 'calcLayerDetAndTrace_row' (mSURF.cpp:217:1) in function 'my::SURF::calcLayerDetAndTrace'." projectName="HLS_SURF_Simplified" solutionName="solution1" date="2020-08-27T17:05:51.480+0800" type="Warning"/>
        <logs message="WARNING: [XFORM 203-561] Updating loop lower bound from 1 to 801 for loop 'calcLayerDetAndTrace_col' (mSURF.cpp:241:1) in function 'my::SURF::calcLayerDetAndTrace'." projectName="HLS_SURF_Simplified" solutionName="solution1" date="2020-08-27T17:05:51.452+0800" type="Warning"/>
        <logs message="WARNING: [XFORM 203-561] Updating loop upper bound from 3 to 1 for loop 'findCharacteristicPoint_layer' (mSURF.cpp:393:1) in function 'my::SURF::findCharacteristicPoint'." projectName="HLS_SURF_Simplified" solutionName="solution1" date="2020-08-27T17:05:51.439+0800" type="Warning"/>
        <logs message="WARNING: [XFORM 203-1103] Ignored data pack directive on non-struct variable 'img.data_stream.V' (top.cpp:27)." projectName="HLS_SURF_Simplified" solutionName="solution1" date="2020-08-27T17:05:51.381+0800" type="Warning"/>
        <logs message="WARNING: [SYNCHK 200-23] mSURF.cpp:427: variable-indexed range selection may cause suboptimal QoR." projectName="HLS_SURF_Simplified" solutionName="solution1" date="2020-08-27T17:04:30.859+0800" type="Warning"/>
        <logs message="WARNING: [HLS 200-471] Dataflow form checks found 1 issue(s) in file top.cpp" projectName="HLS_SURF_Simplified" solutionName="solution1" date="2020-08-27T17:02:45.482+0800" type="Warning"/>
        <logs message="WARNING: [HLS 214-113] Variables defined outside dataflow region are not supported: top.cpp:34:50" projectName="HLS_SURF_Simplified" solutionName="solution1" date="2020-08-27T17:02:35.830+0800" type="Warning"/>
      </synLog>
      <simLog/>
      <mgLog/>
      <packageLog/>
      <csimLog/>
    </logs>
  </warningLogs>
</vivadoHLSLog:LogRoot>
